FortiCare/__init__.py
FortiCare/fortiCare.py
FortiCare/rateLimit.py
FortiCare-1.0.2.dist-info/LICENSE
FortiCare-1.0.2.dist-info/METADATA
FortiCare-1.0.2.dist-info/WHEEL
FortiCare-1.0.2.dist-info/top_level.txt
FortiCare-1.0.2.dist-info/RECORD
