Metadata-Version: 2.1
Name: FortiCare
Version: 1.0.2
Summary: FortiCare management package for python
Home-page: https://pypi.org/project/FortiCare/
Author: See "Authors" section
Author-email: 
License: MIT
Platform: UNKNOWN
Classifier: Programming Language :: Python :: 3
Classifier: License :: OSI Approved :: MIT License
Classifier: Operating System :: OS Independent
Requires-Python: >=3.6
Requires-Dist: requests
Requires-Dist: python-dateutil
Requires-Dist: PyPDF2
Requires-Dist: tabulate
Requires-Dist: filelock
Requires-Dist: validators
